{
  "data": {
    "article": {},
    "attachments": {},
    "author_id": "1962425480612851712",
    "conversation_id": "1986525473271324711",
    "created_at": "2025-11-07T13:46:59.000Z",
    "edit_controls": {
      "editable_until": "2025-11-07T14:46:59.000Z",
      "edits_remaining": 5,
      "is_edit_eligible": false
    },
    "edit_history_tweet_ids": [
      "1986792500087189566"
    ],
    "entities": {
      "mentions": [
        {
          "end": 12,
          "id": "1810642408423747584",
          "start": 0,
          "username": "Honoka8964_"
        }
      ]
    },
    "geo": {},
    "id": "1986792500087189566",
    "in_reply_to_user_id": "1810642408423747584",
    "lang": "zh",
    "note_tweet": {
      "entities": {}
    },
    "possibly_sensitive": false,
    "public_metrics": {
      "bookmark_count": 0,
      "impression_count": 0,
      "like_count": 0,
      "quote_count": 0,
      "reply_count": 0,
      "retweet_count": 0
    },
    "referenced_tweets": [
      {
        "id": "1986779289174589660",
        "type": "replied_to"
      }
    ],
    "reply_settings": "everyone",
    "text": "@Honoka8964_ 可以，也适合"
  },
  "includes": {
    "tweets": [
      {
        "article": {},
        "attachments": {},
        "author_id": "1962425480612851712",
        "conversation_id": "1986525473271324711",
        "created_at": "2025-11-07T13:46:59.000Z",
        "edit_controls": {
          "editable_until": "2025-11-07T14:46:59.000Z",
          "edits_remaining": 5,
          "is_edit_eligible": false
        },
        "edit_history_tweet_ids": [
          "1986792500087189566"
        ],
        "entities": {
          "mentions": [
            {
              "end": 12,
              "id": "1810642408423747584",
              "start": 0,
              "username": "Honoka8964_"
            }
          ]
        },
        "geo": {},
        "id": "1986792500087189566",
        "in_reply_to_user_id": "1810642408423747584",
        "lang": "zh",
        "note_tweet": {
          "entities": {}
        },
        "possibly_sensitive": false,
        "public_metrics": {
          "bookmark_count": 0,
          "impression_count": 0,
          "like_count": 0,
          "quote_count": 0,
          "reply_count": 0,
          "retweet_count": 0
        },
        "referenced_tweets": [
          {
            "id": "1986779289174589660",
            "type": "replied_to"
          }
        ],
        "reply_settings": "everyone",
        "text": "@Honoka8964_ 可以，也适合"
      },
      {
        "article": {},
        "attachments": {},
        "author_id": "1810642408423747584",
        "conversation_id": "1986525473271324711",
        "created_at": "2025-11-07T12:54:29.000Z",
        "edit_controls": {
          "editable_until": "2025-11-07T13:54:29.000Z",
          "edits_remaining": 5,
          "is_edit_eligible": false
        },
        "edit_history_tweet_ids": [
          "1986779289174589660"
        ],
        "entities": {
          "mentions": [
            {
              "end": 11,
              "id": "1962425480612851712",
              "start": 0,
              "username": "yaowubaike"
            }
          ]
        },
        "geo": {},
        "id": "1986779289174589660",
        "in_reply_to_user_id": "1962425480612851712",
        "lang": "zh",
        "note_tweet": {
          "entities": {}
        },
        "possibly_sensitive": false,
        "public_metrics": {
          "bookmark_count": 0,
          "impression_count": 4,
          "like_count": 0,
          "quote_count": 0,
          "reply_count": 1,
          "retweet_count": 0
        },
        "referenced_tweets": [
          {
            "id": "1986525473271324711",
            "type": "replied_to"
          }
        ],
        "reply_settings": "everyone",
        "text": "@yaowubaike 那记忆力差的可以吃吗 医学剂量"
      }
    ],
    "users": [
      {
        "created_at": "2025-09-01T08:02:36.000Z",
        "description": "这里是药物百科官方账号 有报告欢迎私信投稿 | wiki主沐雨@drug_artist1 | 副wiki主小鸮:@Manglesuki｜提供免费药物咨询｜提问箱:https://t.co/LsyPFMc5Pb",
        "entities": {
          "description": {
            "mentions": [
              {
                "end": 44,
                "start": 31,
                "username": "drug_artist1"
              },
              {
                "end": 67,
                "start": 56,
                "username": "Manglesuki"
              }
            ],
            "urls": [
              {
                "display_url": "ngl.link/drug_artist",
                "end": 104,
                "expanded_url": "https://ngl.link/drug_artist",
                "start": 81,
                "url": "https://t.co/LsyPFMc5Pb"
              }
            ]
          },
          "url": {
            "urls": [
              {
                "display_url": "yaowubaike.ca",
                "end": 23,
                "expanded_url": "http://yaowubaike.ca",
                "start": 0,
                "url": "https://t.co/05EG4MjwrN"
              }
            ]
          }
        },
        "id": "1962425480612851712",
        "location": "Xanax天国2mg市",
        "name": "药物百科Mediwiki",
        "pinned_tweet_id": "1975782494189601080",
        "profile_image_url": "https://pbs.twimg.com/profile_images/1962426785532170240/hz3rO6fL_normal.jpg",
        "protected": false,
        "public_metrics": {
          "followers_count": 1537,
          "following_count": 30,
          "like_count": 324,
          "listed_count": 4,
          "media_count": 34,
          "tweet_count": 169
        },
        "url": "https://t.co/05EG4MjwrN",
        "username": "yaowubaike",
        "verified": false
      },
      {
        "created_at": "2024-07-09T11:49:34.000Z",
        "description": "08｜女高｜保持快乐ovo｜对象哥@jingluo728",
        "entities": {
          "description": {
            "mentions": [
              {
                "end": 28,
                "start": 17,
                "username": "jingluo728"
              }
            ]
          }
        },
        "id": "1810642408423747584",
        "location": "距离您0.1km",
        "name": "ほのか",
        "pinned_tweet_id": "1977168162039947321",
        "profile_image_url": "https://pbs.twimg.com/profile_images/1984128170682118144/6R-hPHb5_normal.jpg",
        "protected": false,
        "public_metrics": {
          "followers_count": 260,
          "following_count": 349,
          "like_count": 8587,
          "listed_count": 2,
          "media_count": 308,
          "tweet_count": 2963
        },
        "username": "Honoka8964_",
        "verified": false
      }
    ]
  }
}